lynq/__init__.py
lynq/__main__.py
lynq/backendutils/app/app.py
lynq/backendutils/app/appobject.py
lynq/backendutils/app/basinapp.py
lynq/backendutils/app/blankslateobject.py
lynq/backendutils/app/jsonapp.py
lynq/backendutils/app/remoteapp.py
lynq/backendutils/app/standardappexportobject.py
lynq/backendutils/app/supportedtags.py
lynq/backendutils/app/supportswith.py
lynq/backendutils/app/tagobject.py
lynq/backendutils/app/yamlapp.py
lynq/backendutils/app/__pycache__/app.cpython-312.pyc
lynq/backendutils/app/__pycache__/appobject.cpython-312.pyc
lynq/backendutils/app/__pycache__/basinapp.cpython-312.pyc
lynq/backendutils/app/__pycache__/blankslateobject.cpython-312.pyc
lynq/backendutils/app/__pycache__/jsonapp.cpython-312.pyc
lynq/backendutils/app/__pycache__/remoteapp.cpython-312.pyc
lynq/backendutils/app/__pycache__/standardappexportobject.cpython-312.pyc
lynq/backendutils/app/__pycache__/supportedtags.cpython-312.pyc
lynq/backendutils/app/__pycache__/supportswith.cpython-312.pyc
lynq/backendutils/app/__pycache__/yamlapp.cpython-312.pyc
lynq/backendutils/basin/basinreturnobject.py
lynq/backendutils/basin/getval.py
lynq/backendutils/basin/object.py
lynq/backendutils/basin/__pycache__/basinreturnobject.cpython-312.pyc
lynq/backendutils/basin/__pycache__/getval.cpython-312.pyc
lynq/backendutils/basin/__pycache__/object.cpython-312.pyc
lynq/backendutils/cli/__main__.py
lynq/backendutils/cli/__pycache__/__main__.cpython-312.pyc
lynq/backendutils/launcher/direct.py
lynq/backendutils/launcher/launch.py
lynq/backendutils/launcher/__pycache__/direct.cpython-312.pyc
lynq/backendutils/launcher/__pycache__/launch.cpython-312.pyc
lynq/backendutils/lynq/lynqserverorrelated.py
lynq/backendutils/lynq/manualrungui.py
lynq/backendutils/lynq/msie.py
lynq/backendutils/lynq/pwsh.py
lynq/backendutils/lynq/pycache_remover.py
lynq/backendutils/lynq/rungui.py
lynq/backendutils/lynq/__pycache__/lynqserverorrelated.cpython-312.pyc
lynq/backendutils/lynq/__pycache__/msie.cpython-312.pyc
lynq-10.2.dist-info/LICENSE
lynq-10.2.dist-info/METADATA
lynq-10.2.dist-info/WHEEL
lynq-10.2.dist-info/top_level.txt
lynq-10.2.dist-info/RECORD
