Metadata-Version: 2.1
Name: lynq
Version: 10.2
Summary: Hosting local servers easily, smooth as butter.
Home-page: https://github.com/elemenom/lynq
Author: Elekk (elemenom)
Author-email: pixilreal@gmail.com
License: GPLv3
Classifier: Programming Language :: Python :: 3
Classifier: License :: OSI Approved :: GNU General Public License v3 (GPLv3)
Classifier: Operating System :: OS Independent
Requires-Python: >=3.12
License-File: LICENSE
Requires-Dist: pyyaml
